grideye/__init__.py
grideye/conversion.py
grideye/grideye.py
grideye/py.typed
grideye_driver-0.1.1.dist-info/LICENSE
grideye_driver-0.1.1.dist-info/METADATA
grideye_driver-0.1.1.dist-info/WHEEL
grideye_driver-0.1.1.dist-info/top_level.txt
grideye_driver-0.1.1.dist-info/zip-safe
grideye_driver-0.1.1.dist-info/RECORD
