Metadata-Version: 2.2
Name: grideye-driver
Version: 0.1.1
Summary: Python driver for the Panasonic AMG88 Grid-EYE infrared array sensor
Home-page: https://github.com/rogiervandergeer/grideye-driver
Author: Rogier van der Geer
Author-email: rogier@vander-geer.nl
License: Apache License 2.0
Classifier: Programming Language :: Python :: 3
Classifier: License :: OSI Approved :: Apache Software License
Classifier: Topic :: System :: Hardware :: Hardware Drivers
Classifier: Typing :: Typed
License-File: LICENSE
Requires-Dist: smbus2>=0.3.0
